<?xml version="1.0" encoding="utf-8" ?>
<dwsync>
<file name="ChainDefinitionDiscovery.php" server="50.115.112.212" local="131498110200000000" remote="131522423400000000" />
<file name="DefinitionDiscoveryFactory.php" server="50.115.112.212" local="131498110200000000" remote="131522423400000000" />
<file name="DefinitionDiscoveryInterface.php" server="50.115.112.212" local="131498110200000000" remote="131522423400000000" />
<file name="FileDefinitionDiscovery.php" server="50.115.112.212" local="131498110200000000" remote="131522423400000000" />
<file name="FileDefinitionDiscoveryBase.php" server="50.115.112.212" local="131498110200000000" remote="131522423400000000" />
<file name="GuzzleDefinitionDiscovery.php" server="50.115.112.212" local="131498110200000000" remote="131522423400000000" />
<file name="WritableDefinitionDiscoveryInterface.php" server="50.115.112.212" local="131498110200000000" remote="131522423400000000" />
<file name="WritableFileDefinitionDiscovery.php" server="50.115.112.212" local="131498110200000000" remote="131522423400000000" />
</dwsync>